isofier/__init__.py
isofier/iso.py
isofier-1.0.dist-info/METADATA
isofier-1.0.dist-info/WHEEL
isofier-1.0.dist-info/top_level.txt
isofier-1.0.dist-info/RECORD
